redbox/__init__.py
redbox/args.py
redbox/defaults.py
redbox/prometheus.py
redbox/config/__init__.py
redbox/config/config.py
redbox/config/template.py
redbox/config/types/__init__.py
redbox/config/types/ds_config.py
redbox/request/__init__.py
redbox/request/conditions.py
redbox/request/request_simple.py
redbox/request/classes/__init__.py
redbox/request/classes/request.py
redbox/request/types/__init__.py
redbox/types/__init__.py
redbox/types/ds_response.py
redbox/types/ds_target.py
prometheus_redbox_exporter-0.1.3.dist-info/LICENSE.txt
prometheus_redbox_exporter-0.1.3.dist-info/METADATA
prometheus_redbox_exporter-0.1.3.dist-info/WHEEL
prometheus_redbox_exporter-0.1.3.dist-info/entry_points.txt
prometheus_redbox_exporter-0.1.3.dist-info/top_level.txt
prometheus_redbox_exporter-0.1.3.dist-info/RECORD
