Metadata-Version: 2.1
Name: prometheus-redbox-exporter
Version: 0.1.3
Summary: Prometheus exporter that throws stuff to httpd endpoints and evaluates their response.
Home-page: https://github.com/cytopia/prometheus-redbox_exporter
Author: cytopia
Author-email: cytopia@everythingcli.org
License: MIT
Keywords: prometheus,redbox_exporter,redbox,blackbox,blackbox_exporter
Platform: UNKNOWN
Classifier: License :: OSI Approved :: MIT License
Classifier: Programming Language :: Python :: 3
Requires-Python: >3.5.2
Requires-Dist: PyYAML
Requires-Dist: requests
